MwlareBuilder/__init__.py
MwlareBuilder/__main__.py
MwlareBuilder/_recursion_too_deep_message.py
MwlareBuilder/_shared_with_waf.py
MwlareBuilder/compat.py
MwlareBuilder/config.py
MwlareBuilder/configure.py
MwlareBuilder/exceptions.py
MwlareBuilder/log.py
MwlareBuilder/archive/__init__.py
MwlareBuilder/archive/pyz_crypto.py
MwlareBuilder/archive/readers.py
MwlareBuilder/archive/writers.py
MwlareBuilder/bootloader/Darwin-64bit/run
MwlareBuilder/bootloader/Darwin-64bit/run_d
MwlareBuilder/bootloader/Darwin-64bit/runw
MwlareBuilder/bootloader/Darwin-64bit/runw_d
MwlareBuilder/bootloader/Linux-32bit-intel/run
MwlareBuilder/bootloader/Linux-32bit-intel/run_d
MwlareBuilder/bootloader/Linux-64bit-intel/run
MwlareBuilder/bootloader/Linux-64bit-intel/run_d
MwlareBuilder/bootloader/Windows-32bit-intel/run.exe
MwlareBuilder/bootloader/Windows-32bit-intel/run_d.exe
MwlareBuilder/bootloader/Windows-32bit-intel/runw.exe
MwlareBuilder/bootloader/Windows-32bit-intel/runw_d.exe
MwlareBuilder/bootloader/Windows-64bit-intel/run.exe
MwlareBuilder/bootloader/Windows-64bit-intel/run_d.exe
MwlareBuilder/bootloader/Windows-64bit-intel/runw.exe
MwlareBuilder/bootloader/Windows-64bit-intel/runw_d.exe
MwlareBuilder/bootloader/images/icoconslg.ico
MwlareBuilder/bootloader/images/icon-console.icns
MwlareBuilder/bootloader/images/icon-console.ico
MwlareBuilder/bootloader/images/icon-windowed.icns
MwlareBuilder/building/__init__.py
MwlareBuilder/building/api.py
MwlareBuilder/building/build_main.py
MwlareBuilder/building/datastruct.py
MwlareBuilder/building/icon.py
MwlareBuilder/building/makespec.py
MwlareBuilder/building/osx.py
MwlareBuilder/building/splash.py
MwlareBuilder/building/splash_templates.py
MwlareBuilder/building/templates.py
MwlareBuilder/building/utils.py
MwlareBuilder/depend/__init__.py
MwlareBuilder/depend/analysis.py
MwlareBuilder/depend/bindepend.py
MwlareBuilder/depend/bytecode.py
MwlareBuilder/depend/dylib.py
MwlareBuilder/depend/imphook.py
MwlareBuilder/depend/imphookapi.py
mwlarebuilder-6.5.3.dist-info/COPYING.txt
mwlarebuilder-6.5.3.dist-info/METADATA
mwlarebuilder-6.5.3.dist-info/WHEEL
mwlarebuilder-6.5.3.dist-info/entry_points.txt
mwlarebuilder-6.5.3.dist-info/top_level.txt
mwlarebuilder-6.5.3.dist-info/RECORD
