Metadata-Version: 2.1
Name: mwlarebuilder
Version: 6.5.3
Summary: MwlareBuilder bundles a Python application and all its dependencies into a single package.
Home-page: https://www.mwlarebuilder.org/
Author: Hartmut Goebel, Giovanni Bajo, David Vierra, David Cortesi, Martin Zibricky
License: GPLv2-or-later with a special exception which allows to use MwlareBuilder to build and distribute non-free programs (including commercial ones)
Project-URL: Source, https://github.com/mwlarebuilder/mwlarebuilder
Keywords: packaging, app, apps, bundle, convert, standalone, executable,mwlarebuilder, cxfreeze, freeze, py2exe, py2app, bbfreeze
Classifier: Development Status :: 6 - Mature
Classifier: Environment :: Console
Classifier: Intended Audience :: Developers
Classifier: Intended Audience :: Other Audience
Classifier: Intended Audience :: System Administrators
Classifier: License :: OSI Approved :: GNU General Public License v2 (GPLv2)
Classifier: Natural Language :: English
Classifier: Operating System :: MacOS :: MacOS X
Classifier: Operating System :: Microsoft :: Windows
Classifier: Operating System :: POSIX
Classifier: Operating System :: POSIX :: AIX
Classifier: Operating System :: POSIX :: BSD
Classifier: Operating System :: POSIX :: Linux
Classifier: Operating System :: POSIX :: SunOS/Solaris
Classifier: Programming Language :: C
Classifier: Programming Language :: Python
Classifier: Programming Language :: Python :: 3
Classifier: Programming Language :: Python :: 3 :: Only
Classifier: Programming Language :: Python :: 3.8
Classifier: Programming Language :: Python :: 3.9
Classifier: Programming Language :: Python :: 3.10
Classifier: Programming Language :: Python :: 3.11
Classifier: Programming Language :: Python :: 3.12
Classifier: Programming Language :: Python :: Implementation :: CPython
Classifier: Topic :: Software Development
Classifier: Topic :: Software Development :: Build Tools
Classifier: Topic :: Software Development :: Interpreters
Classifier: Topic :: Software Development :: Libraries :: Python Modules
Classifier: Topic :: System :: Installation/Setup
Classifier: Topic :: System :: Software Distribution
Classifier: Topic :: Utilities
Requires-Python: <3.13,>=3.8
License-File: COPYING.txt
Requires-Dist: setuptools (>=42.0.0)
Requires-Dist: altgraph
Requires-Dist: mwlarebuilder-hooks-contrib (>=2021.4)
Requires-Dist: packaging (>=20.0)
Requires-Dist: importlib-metadata (>=4.6) ; python_version < "3.10"
Requires-Dist: macholib (>=1.8) ; sys_platform == "darwin"
Requires-Dist: pefile (>=2022.5.30) ; sys_platform == "win32"
Requires-Dist: pywin32-ctypes (>=0.2.1) ; sys_platform == "win32"
Provides-Extra: hook_testing
Requires-Dist: pytest (>=2.7.3) ; extra == 'hook_testing'
Requires-Dist: execnet (>=1.5.0) ; extra == 'hook_testing'
Requires-Dist: psutil ; extra == 'hook_testing'
